[{"line":2,"elements":[{"line":3,"name":"user goes to google","description":"","type":"background","keyword":"Background","steps":[{"result":{"duration":3300385300,"status":"passed"},"line":4,"name":"user navigates to \"https://google.com\"","match":{"arguments":[{"val":"\"https://google.com\"","offset":18}],"location":"stepdefinitions.CommonStepDefs.user_navigates_to(java.lang.String)"},"keyword":"Given "}]},{"start_timestamp":"2023-06-21T13:23:32.515Z","line":6,"name":"TC01_iphone_search","description":"","id":"search-feature;tc01-iphone-search","type":"scenario","keyword":"Scenario","steps":[{"result":{"duration":314165300,"status":"passed"},"line":7,"name":"user search for \"iPhone\"","match":{"arguments":[{"val":"\"iPhone\"","offset":16}],"location":"stepdefinitions.GoogleStepDefs.user_search_for(java.lang.String)"},"keyword":"And "},{"result":{"duration":2820876000,"status":"passed"},"line":8,"name":"verify the page title contains \"iPhone\"","match":{"arguments":[{"val":"\"iPhone\"","offset":31}],"location":"stepdefinitions.CommonStepDefs.verify_the_page_title_contains(java.lang.String)"},"keyword":"Then "},{"result":{"duration":118752700,"status":"passed"},"line":9,"name":"close the application","match":{"location":"stepdefinitions.CommonStepDefs.close_the_application()"},"keyword":"Then "}],"tags":[{"name":"@parameterizing1"},{"name":"@test_runner"}]},{"line":3,"name":"user goes to google","description":"","type":"background","keyword":"Background","steps":[{"result":{"duration":1811353900,"status":"passed"},"line":4,"name":"user navigates to \"https://google.com\"","match":{"arguments":[{"val":"\"https://google.com\"","offset":18}],"location":"stepdefinitions.CommonStepDefs.user_navigates_to(java.lang.String)"},"keyword":"Given "}]},{"start_timestamp":"2023-06-21T13:23:39.088Z","line":12,"name":"TC02_tesla_search","description":"","id":"search-feature;tc02-tesla-search","type":"scenario","keyword":"Scenario","steps":[{"result":{"duration":167028800,"status":"passed"},"line":13,"name":"user search for \"tesla\"","match":{"arguments":[{"val":"\"tesla\"","offset":16}],"location":"stepdefinitions.GoogleStepDefs.user_search_for(java.lang.String)"},"keyword":"And "},{"result":{"duration":2045453500,"status":"passed"},"line":14,"name":"verify the page title contains \"tesla\"","match":{"arguments":[{"val":"\"tesla\"","offset":31}],"location":"stepdefinitions.CommonStepDefs.verify_the_page_title_contains(java.lang.String)"},"keyword":"Then "},{"result":{"duration":111345600,"status":"passed"},"line":15,"name":"close the application","match":{"location":"stepdefinitions.CommonStepDefs.close_the_application()"},"keyword":"Then "}],"tags":[{"name":"@parameterizing1"},{"name":"@test_runner"}]},{"line":3,"name":"user goes to google","description":"","type":"background","keyword":"Background","steps":[{"result":{"duration":3601611500,"status":"passed"},"line":4,"name":"user navigates to \"https://google.com\"","match":{"arguments":[{"val":"\"https://google.com\"","offset":18}],"location":"stepdefinitions.CommonStepDefs.user_navigates_to(java.lang.String)"},"keyword":"Given "}]},{"start_timestamp":"2023-06-21T13:23:43.228Z","line":16,"name":"TC03_bmw_search","description":"","id":"search-feature;tc03-bmw-search","type":"scenario","keyword":"Scenario","steps":[{"result":{"duration":196475500,"status":"passed"},"line":17,"name":"user search for \"bmw\"","match":{"arguments":[{"val":"\"bmw\"","offset":16}],"location":"stepdefinitions.GoogleStepDefs.user_search_for(java.lang.String)"},"keyword":"And "},{"result":{"duration":2322167600,"status":"passed"},"line":18,"name":"verify the page title contains \"bmw\"","match":{"arguments":[{"val":"\"bmw\"","offset":31}],"location":"stepdefinitions.CommonStepDefs.verify_the_page_title_contains(java.lang.String)"},"keyword":"Then "},{"result":{"duration":115957700,"status":"passed"},"line":19,"name":"close the application","match":{"location":"stepdefinitions.CommonStepDefs.close_the_application()"},"keyword":"Then "}],"tags":[{"name":"@parameterizing1"},{"name":"@test_runner"}]},{"line":3,"name":"user goes to google","description":"","type":"background","keyword":"Background","steps":[{"result":{"duration":1825197300,"status":"passed"},"line":4,"name":"user navigates to \"https://google.com\"","match":{"arguments":[{"val":"\"https://google.com\"","offset":18}],"location":"stepdefinitions.CommonStepDefs.user_navigates_to(java.lang.String)"},"keyword":"Given "}]},{"start_timestamp":"2023-06-21T13:23:49.470Z","line":20,"name":"TC04_apple_search","description":"","id":"search-feature;tc04-apple-search","type":"scenario","keyword":"Scenario","steps":[{"result":{"duration":165557400,"status":"passed"},"line":21,"name":"user search for \"apple\"","match":{"arguments":[{"val":"\"apple\"","offset":16}],"location":"stepdefinitions.GoogleStepDefs.user_search_for(java.lang.String)"},"keyword":"And "},{"result":{"duration":2371783700,"status":"passed"},"line":22,"name":"verify the page title contains \"apple\"","match":{"arguments":[{"val":"\"apple\"","offset":31}],"location":"stepdefinitions.CommonStepDefs.verify_the_page_title_contains(java.lang.String)"},"keyword":"Then "},{"result":{"duration":80783800,"status":"passed"},"line":23,"name":"close the application","match":{"location":"stepdefinitions.CommonStepDefs.close_the_application()"},"keyword":"Then "}],"tags":[{"name":"@parameterizing1"},{"name":"@test_runner"}]},{"line":3,"name":"user goes to google","description":"","type":"background","keyword":"Background","steps":[{"result":{"duration":2583375200,"status":"passed"},"line":4,"name":"user navigates to \"https://google.com\"","match":{"arguments":[{"val":"\"https://google.com\"","offset":18}],"location":"stepdefinitions.CommonStepDefs.user_navigates_to(java.lang.String)"},"keyword":"Given "}]},{"start_timestamp":"2023-06-21T13:23:53.918Z","line":24,"name":"TC05_nio_search","description":"","id":"search-feature;tc05-nio-search","type":"scenario","keyword":"Scenario","steps":[{"result":{"duration":174538200,"status":"passed"},"line":25,"name":"user search for \"nio\"","match":{"arguments":[{"val":"\"nio\"","offset":16}],"location":"stepdefinitions.GoogleStepDefs.user_search_for(java.lang.String)"},"keyword":"And "},{"result":{"duration":2021883900,"status":"passed"},"line":26,"name":"verify the page title contains \"nio\"","match":{"arguments":[{"val":"\"nio\"","offset":31}],"location":"stepdefinitions.CommonStepDefs.verify_the_page_title_contains(java.lang.String)"},"keyword":"Then "},{"result":{"duration":79846400,"status":"passed"},"line":27,"name":"close the application","match":{"location":"stepdefinitions.CommonStepDefs.close_the_application()"},"keyword":"Then "}],"tags":[{"name":"@parameterizing1"},{"name":"@test_runner"}]},{"line":3,"name":"user goes to google","description":"","type":"background","keyword":"Background","steps":[{"result":{"duration":1855469100,"status":"passed"},"line":4,"name":"user navigates to \"https://google.com\"","match":{"arguments":[{"val":"\"https://google.com\"","offset":18}],"location":"stepdefinitions.CommonStepDefs.user_navigates_to(java.lang.String)"},"keyword":"Given "}]},{"start_timestamp":"2023-06-21T13:23:58.782Z","line":28,"name":"TC06_pineapple_search","description":"","id":"search-feature;tc06-pineapple-search","type":"scenario","keyword":"Scenario","steps":[{"result":{"duration":196479900,"status":"passed"},"line":29,"name":"user search for \"pine apple\"","match":{"arguments":[{"val":"\"pine apple\"","offset":16}],"location":"stepdefinitions.GoogleStepDefs.user_search_for(java.lang.String)"},"keyword":"And "},{"result":{"duration":2287391300,"status":"passed"},"line":30,"name":"verify the page title contains \"pine apple\"","match":{"arguments":[{"val":"\"pine apple\"","offset":31}],"location":"stepdefinitions.CommonStepDefs.verify_the_page_title_contains(java.lang.String)"},"keyword":"Then "},{"result":{"duration":125687200,"status":"passed"},"line":31,"name":"close the application","match":{"location":"stepdefinitions.CommonStepDefs.close_the_application()"},"keyword":"Then "}],"tags":[{"name":"@parameterizing1"},{"name":"@test_runner"}]}],"name":"search_feature","description":"","id":"search-feature","keyword":"Feature","uri":"file:src/test/resources/features/day27_parameterizing_with_double_quote.feature","tags":[{"name":"@parameterizing1","type":"Tag","location":{"line":1,"column":1}},{"name":"@test_runner","type":"Tag","location":{"line":1,"column":18}}]}]"","match":{"arguments":[{"val":"\"https://google.com\"","offset":18}],"location":"stepdefinitions.CommonStepDefs.user_navigates_to(java.lang.String)"},"keyword":"Given "}]},{"start_timestamp":"2023-06-21T13:23:30.631Z","line":20,"name":"search_scenario","description":"","id":"search-feature;search-scenario;test-data;8","type":"scenario","keyword":"Scenario Outline","steps":[{"result":{"duration":205450200,"status":"passed"},"line":8,"name":"user search for \"nio\"","match":{"arguments":[{"val":"\"nio\"","offset":16}],"location":"stepdefinitions.GoogleStepDefs.user_search_for(java.lang.String)"},"keyword":"And "},{"result":{"duration":2225083000,"status":"passed"},"line":9,"name":"verify the page title contains \"nio\"","match":{"arguments":[{"val":"\"nio\"","offset":31}],"location":"stepdefinitions.CommonStepDefs.verify_the_page_title_contains(java.lang.String)"},"keyword":"Then "},{"result":{"duration":115690300,"status":"passed"},"line":10,"name":"close the application","match":{"location":"stepdefinitions.CommonStepDefs.close_the_application()"},"keyword":"Then "}],"tags":[{"name":"@scenario_outline_1"},{"name":"@smoke_test_runner"}]}],"name":"search_feature","description":"","id":"search-feature","keyword":"Feature","uri":"file:src/test/resources/features/day27_scenario_outline_1.feature","tags":[{"name":"@scenario_outline_1","type":"Tag","location":{"line":1,"column":1}},{"name":"@smoke_test_runner","type":"Tag","location":{"line":1,"column":21}}]}]